mytool_andinet/__init__.py
mytool_andinet/core.py
mytool_andinet-0.1.0.dist-info/WHEEL
mytool_andinet-0.1.0.dist-info/METADATA
mytool_andinet-0.1.0.dist-info/RECORD
