Metadata-Version: 2.4
Name: mytool_andinet
Version: 0.1.0
Summary: My first Python library
Author-email: Andinet abebe <andinetatx@gmail.com>
Requires-Python: >=3.8
Requires-Dist: numpy
